odoo8_addon_l10n_br_stock-8.0.1.0.0.99.dev5-py2.7-nspkg.pth
odoo8_addon_l10n_br_stock-8.0.1.0.0.99.dev5.dist-info/top_level.txt
odoo8_addon_l10n_br_stock-8.0.1.0.0.99.dev5.dist-info/WHEEL
odoo8_addon_l10n_br_stock-8.0.1.0.0.99.dev5.dist-info/RECORD
odoo8_addon_l10n_br_stock-8.0.1.0.0.99.dev5.dist-info/metadata.json
odoo8_addon_l10n_br_stock-8.0.1.0.0.99.dev5.dist-info/DESCRIPTION.rst
odoo8_addon_l10n_br_stock-8.0.1.0.0.99.dev5.dist-info/METADATA
odoo8_addon_l10n_br_stock-8.0.1.0.0.99.dev5.dist-info/namespace_packages.txt
odoo_addons/l10n_br_stock/__openerp__.py
odoo_addons/l10n_br_stock/__init__.py
odoo_addons/l10n_br_stock/README.rst
odoo_addons/l10n_br_stock/models/stock.py
odoo_addons/l10n_br_stock/models/__init__.py
odoo_addons/l10n_br_stock/i18n/pt_BR.po
odoo_addons/l10n_br_stock/views/stock_view.xml
odoo_addons/l10n_br_stock/data/l10n_br_stock_data.xml
odoo_addons/l10n_br_stock/static/description/icon.png
